{
  "stats": {
    "suites": 1,
    "tests": 3,
    "passes": 3,
    "pending": 0,
    "failures": 0,
    "start": "2023-04-27T16:21:59.274Z",
    "end": "2023-04-27T16:22:03.488Z",
    "duration": 4155,
    "testsRegistered": 3,
    "passPercent": 100,
    "pendingPercent": 0,
    "other": 0,
    "hasOther": false,
    "skipped": 0,
    "hasSkipped": false
  },
  "results": [
    {
      "uuid": "a0890c5b-5984-452f-9a75-1d775530292d",
      "title": "",
      "fullFile": "cypress\\integration\\promiseBasic.spec.js",
      "file": "cypress\\integration\\promiseBasic.spec.js",
      "beforeHooks": [],
      "afterHooks": [],
      "tests": [],
      "suites": [
        {
          "uuid": "4e66d172-acd3-4276-bc24-921b8c081c39",
          "title": "Promise basic app",
          "fullFile": "",
          "file": "",
          "beforeHooks": [],
          "afterHooks": [],
          "tests": [
            {
              "title": "should resolve first promise by click on logo",
              "fullTitle": "Promise basic app should resolve first promise by click on logo",
              "timedOut": null,
              "duration": 537,
              "state": "passed",
              "speed": "slow",
              "pass": true,
              "fail": false,
              "pending": false,
              "context": null,
              "code": "cy.get('.logo').click({\n  force: true\n});\ncy.get('.message').contains('Promise was resolved!');",
              "err": {},
              "uuid": "8543ad76-1e82-4180-930c-9c0a2e4a818e",
              "parentUUID": "4e66d172-acd3-4276-bc24-921b8c081c39",
              "isHook": false,
              "skipped": false
            },
            {
              "title": "should reject second promise in 3 seconds",
              "fullTitle": "Promise basic app should reject second promise in 3 seconds",
              "timedOut": null,
              "duration": 3111,
              "state": "passed",
              "speed": "slow",
              "pass": true,
              "fail": false,
              "pending": false,
              "context": null,
              "code": "cy.get('.error-message', {\n  timeout: 3000\n}).contains('Promise was rejected!');",
              "err": {},
              "uuid": "cad825a8-9950-41b3-b65d-c52e95b2b1e1",
              "parentUUID": "4e66d172-acd3-4276-bc24-921b8c081c39",
              "isHook": false,
              "skipped": false
            },
            {
              "title": "shouldn't resolve any promise by right click",
              "fullTitle": "Promise basic app shouldn't resolve any promise by right click",
              "timedOut": null,
              "duration": 507,
              "state": "passed",
              "speed": "slow",
              "pass": true,
              "fail": false,
              "pending": false,
              "context": null,
              "code": "cy.get('.logo').rightclick({\n  force: true\n});\ncy.get('.message').should('not.visible');",
              "err": {},
              "uuid": "015d5f0b-db58-4ae2-9d1a-3a63f31bda53",
              "parentUUID": "4e66d172-acd3-4276-bc24-921b8c081c39",
              "isHook": false,
              "skipped": false
            }
          ],
          "suites": [],
          "passes": [
            "8543ad76-1e82-4180-930c-9c0a2e4a818e",
            "cad825a8-9950-41b3-b65d-c52e95b2b1e1",
            "015d5f0b-db58-4ae2-9d1a-3a63f31bda53"
          ],
          "failures": [],
          "pending": [],
          "skipped": [],
          "duration": 4155,
          "root": false,
          "rootEmpty": false,
          "_timeout": 2000
        }
      ],
      "passes": [],
      "failures": [],
      "pending": [],
      "skipped": [],
      "duration": 0,
      "root": true,
      "rootEmpty": true,
      "_timeout": 2000
    }
  ],
  "meta": {
    "mocha": {
      "version": "7.0.1"
    },
    "mochawesome": {
      "options": {
        "quiet": false,
        "reportFilename": "mochawesome",
        "saveHtml": false,
        "saveJson": true,
        "consoleReporter": "spec",
        "useInlineDiffs": false,
        "code": true
      },
      "version": "6.2.1"
    },
    "marge": {
      "options": {
        "reportDir": "raw_reports",
        "overwrite": false,
        "html": false,
        "json": true
      },
      "version": "5.1.0"
    }
  }
}